{"commitInfo":{"timestamp":1741533714202,"operation":"WRITE","operationParameters":{"mode":"Overwrite","partitionBy":"[]"},"isolationLevel":"Serializable","isBlindAppend":false,"operationMetrics":{"numFiles":"1","numOutputRows":"5","numOutputBytes":"787"},"engineInfo":"Apache-Spark/3.3.2 Delta-Lake/2.2.0","txnId":"cea38126-547a-465d-9d30-a11b3b9163a7"}}
{"protocol":{"minReaderVersion":1,"minWriterVersion":2}}
{"metaData":{"id":"808d508c-f0cd-4d3b-a54f-f4c6970bfb8a","format":{"provider":"parquet","options":{}},"schemaString":"{\"type\":\"struct\",\"fields\":[{\"name\":\"REGION_ID\",\"type\":\"integer\",\"nullable\":true,\"metadata\":{}},{\"name\":\"REGION_NAME\",\"type\":\"string\",\"nullable\":true,\"metadata\":{}}]}","partitionColumns":[],"configuration":{},"createdTime":1741533713414}}
{"add":{"path":"part-00000-39a0aaba-210a-40b0-92b0-a9b2d826c5a5-c000.snappy.parquet","partitionValues":{},"size":787,"modificationTime":1741533713924,"dataChange":true,"stats":"{\"numRecords\":5,\"minValues\":{\"REGION_ID\":10,\"REGION_NAME\":\"Africa\"},\"maxValues\":{\"REGION_ID\":50,\"REGION_NAME\":\"Oceania\"},\"nullCount\":{\"REGION_ID\":0,\"REGION_NAME\":0}}"}}
